traceloop/sdk/__init__.py
traceloop/sdk/fetcher.py
traceloop/sdk/instruments.py
traceloop/sdk/py.typed
traceloop/sdk/version.py
traceloop/sdk/annotation/__init__.py
traceloop/sdk/annotation/base_annotation.py
traceloop/sdk/annotation/user_feedback.py
traceloop/sdk/associations/__init__.py
traceloop/sdk/associations/associations.py
traceloop/sdk/client/__init__.py
traceloop/sdk/client/client.py
traceloop/sdk/client/http.py
traceloop/sdk/config/__init__.py
traceloop/sdk/datasets/__init__.py
traceloop/sdk/datasets/attachment.py
traceloop/sdk/datasets/base.py
traceloop/sdk/datasets/column.py
traceloop/sdk/datasets/dataset.py
traceloop/sdk/datasets/datasets.py
traceloop/sdk/datasets/model.py
traceloop/sdk/datasets/row.py
traceloop/sdk/decorators/__init__.py
traceloop/sdk/decorators/base.py
traceloop/sdk/evaluator/__init__.py
traceloop/sdk/evaluator/config.py
traceloop/sdk/evaluator/evaluator.py
traceloop/sdk/evaluator/field_mapping.py
traceloop/sdk/evaluator/model.py
traceloop/sdk/evaluator/stream_client.py
traceloop/sdk/experiment/__init__.py
traceloop/sdk/experiment/experiment.py
traceloop/sdk/experiment/model.py
traceloop/sdk/experiment/utils.py
traceloop/sdk/generated/__init__.py
traceloop/sdk/generated/evaluators/__init__.py
traceloop/sdk/generated/evaluators/definitions.py
traceloop/sdk/generated/evaluators/registry.py
traceloop/sdk/generated/evaluators/request.py
traceloop/sdk/generated/evaluators/response.py
traceloop/sdk/guardrails/__init__.py
traceloop/sdk/guardrails/guardrails.py
traceloop/sdk/guardrails/types.py
traceloop/sdk/images/image_uploader.py
traceloop/sdk/logging/__init__.py
traceloop/sdk/logging/logging.py
traceloop/sdk/metrics/__init__.py
traceloop/sdk/metrics/metrics.py
traceloop/sdk/prompts/__init__.py
traceloop/sdk/prompts/client.py
traceloop/sdk/prompts/model.py
traceloop/sdk/prompts/registry.py
traceloop/sdk/tracing/__init__.py
traceloop/sdk/tracing/content_allow_list.py
traceloop/sdk/tracing/context_manager.py
traceloop/sdk/tracing/manual.py
traceloop_sdk-0.51.1.dist-info/METADATA
traceloop_sdk-0.51.1.dist-info/WHEEL
traceloop_sdk-0.51.1.dist-info/RECORD
